kelvin/sdk/py.typed
kelvin/sdk/cli/__init__.py
kelvin/sdk/cli/__main__.py
kelvin/sdk/cli/app.py
kelvin/sdk/cli/appregistry.py
kelvin/sdk/cli/apps.py
kelvin/sdk/cli/authentication.py
kelvin/sdk/cli/configuration.py
kelvin/sdk/cli/ksdk.py
kelvin/sdk/cli/mlflow.py
kelvin/sdk/cli/secret.py
kelvin/sdk/cli/system_report.py
kelvin/sdk/cli/version.py
kelvin/sdk/cli/workload.py
kelvin/sdk/interface/__init__.py
kelvin/sdk/interface/app.py
kelvin/sdk/interface/apps.py
kelvin/sdk/interface/authentication.py
kelvin/sdk/interface/configuration.py
kelvin/sdk/interface/schema.py
kelvin/sdk/interface/secret.py
kelvin/sdk/interface/system_report.py
kelvin/sdk/interface/workload.py
kelvin/sdk/lib/__init__.py
kelvin/sdk/lib/exceptions.py
kelvin/sdk/lib/api/__init__.py
kelvin/sdk/lib/api/app_workloads.py
kelvin/sdk/lib/api/apps.py
kelvin/sdk/lib/api/secret.py
kelvin/sdk/lib/apps/__init__.py
kelvin/sdk/lib/apps/local_apps_manager.py
kelvin/sdk/lib/auth/__init__.py
kelvin/sdk/lib/auth/credential_manager.py
kelvin/sdk/lib/configs/__init__.py
kelvin/sdk/lib/configs/auth_manager_configs.py
kelvin/sdk/lib/configs/click_configs.py
kelvin/sdk/lib/configs/docker_configs.py
kelvin/sdk/lib/configs/emulation_configs.py
kelvin/sdk/lib/configs/general_configs.py
kelvin/sdk/lib/configs/pypi_configs.py
kelvin/sdk/lib/configs/schema_manager_configs.py
kelvin/sdk/lib/docker/__init__.py
kelvin/sdk/lib/docker/docker_manager.py
kelvin/sdk/lib/docker/docker_utils.py
kelvin/sdk/lib/mlflow/__init__.py
kelvin/sdk/lib/mlflow/mlflow.py
kelvin/sdk/lib/models/__init__.py
kelvin/sdk/lib/models/generic.py
kelvin/sdk/lib/models/ksdk_docker.py
kelvin/sdk/lib/models/ksdk_global_configuration.py
kelvin/sdk/lib/models/operation.py
kelvin/sdk/lib/models/types.py
kelvin/sdk/lib/models/apps/__init__.py
kelvin/sdk/lib/models/apps/bridge_app.py
kelvin/sdk/lib/models/apps/common.py
kelvin/sdk/lib/models/apps/docker_app.py
kelvin/sdk/lib/models/apps/kelvin_app.py
kelvin/sdk/lib/models/apps/ksdk_app_configuration.py
kelvin_sdk-9.4.2.dist-info/licenses/LICENSE.txt
kelvin_sdk-9.4.2.dist-info/METADATA
kelvin_sdk-9.4.2.dist-info/WHEEL
kelvin_sdk-9.4.2.dist-info/entry_points.txt
kelvin_sdk-9.4.2.dist-info/top_level.txt
kelvin_sdk-9.4.2.dist-info/RECORD
