Metadata-Version: 2.4
Name: kelvin-sdk
Version: 9.4.2
Summary: CLI tool to interact with Kelvin platform
Author-email: Kelvin Inc <engineering@kelvininc.com>
Project-URL: Homepage, https://kelvin.ai/
Classifier: Operating System :: OS Independent
Classifier: Programming Language :: Python :: 3
Requires-Python: <3.14,>=3.9
License-File: LICENSE.txt
Requires-Dist: click==8.*
Requires-Dist: pydantic[email]==2.11.*
Requires-Dist: docker==7.*
Requires-Dist: python-on-whales==0.75.*
Requires-Dist: PyYAML==6.*
Requires-Dist: ruamel.yaml==0.*
Requires-Dist: typing-extensions==4.*
Requires-Dist: structlog==23.*
Requires-Dist: tabulate==0.*
Requires-Dist: traitlets==5.*
Requires-Dist: colorama==0.*
Requires-Dist: jsonschema==4.*
Requires-Dist: tqdm==4.*
Requires-Dist: filelock==3.*
Requires-Dist: requests==2.*
Requires-Dist: humanize==4.*
Requires-Dist: psutil==6.*
Requires-Dist: typeguard==4.*
Requires-Dist: jinja2==3.*
Requires-Dist: docker-image-py==0.*
Requires-Dist: importlib-resources==6.*
Requires-Dist: setuptools>=80
Requires-Dist: pip
Requires-Dist: platformdirs==4.*
Requires-Dist: keyring==25.*
Requires-Dist: keyrings.alt==5.*
Requires-Dist: kelvin-python-sdk[ai,publisher]<0.4,>=0.3.1
Requires-Dist: kelvin-python-api-client<2.0,>=1.0.1
Provides-Extra: mlflow
Requires-Dist: mlflow==3.*; extra == "mlflow"
Requires-Dist: inquirer==3.2.*; extra == "mlflow"
Dynamic: license-file
